rabbit_handler_kvg/__init__.py
rabbit_handler_kvg/rabbit_handler_kvg.py
rabbit_handler_kvg-1.0.0.dist-info/METADATA
rabbit_handler_kvg-1.0.0.dist-info/WHEEL
rabbit_handler_kvg-1.0.0.dist-info/top_level.txt
rabbit_handler_kvg-1.0.0.dist-info/RECORD
